starrailres/__init__.py
starrailres/index.py
starrailres/models/avatars.py
starrailres/models/characters.py
starrailres/models/common.py
starrailres/models/descriptions.py
starrailres/models/elements.py
starrailres/models/info.py
starrailres/models/items.py
starrailres/models/light_cones.py
starrailres/models/paths.py
starrailres/models/properties.py
starrailres/models/relics.py
starrailres/utils.py
starrailres-3.6.0.dist-info/LICENSE
starrailres-3.6.0.dist-info/METADATA
starrailres-3.6.0.dist-info/WHEEL
starrailres-3.6.0.dist-info/RECORD
