Metadata-Version: 2.1
Name: starrailres
Version: 3.6.0
Summary: StarRailRes parse package
Home-page: https://github.com/Mar-7th/starrailres.py
License: MIT
Author: mobyw
Author-email: mobyw66@gmail.com
Requires-Python: >=3.9,<4.0
Classifier: License :: OSI Approved :: MIT License
Classifier: Programming Language :: Python :: 3
Classifier: Programming Language :: Python :: 3.9
Classifier: Programming Language :: Python :: 3.10
Classifier: Programming Language :: Python :: 3.11
Classifier: Programming Language :: Python :: 3.12
Requires-Dist: msgspec (>=0.19.0,<0.20.0)
Project-URL: Repository, https://github.com/Mar-7th/starrailres.py
